XStatic_AnyWikiDraw-0.14.2-py3.13-nspkg.pth
xstatic/pkg/anywikidraw/__init__.py
xstatic/pkg/anywikidraw/__init__.py~
xstatic/pkg/anywikidraw/data/AnyWikiDrawForMoinMoin.jar
xstatic/pkg/anywikidraw/data/AnyWikiDrawForMoinMoin.jar.pack.gz
xstatic_anywikidraw-0.14.2.dist-info/METADATA
xstatic_anywikidraw-0.14.2.dist-info/WHEEL
xstatic_anywikidraw-0.14.2.dist-info/namespace_packages.txt
xstatic_anywikidraw-0.14.2.dist-info/top_level.txt
xstatic_anywikidraw-0.14.2.dist-info/RECORD
