Metadata-Version: 2.4
Name: XStatic-AnyWikiDraw
Version: 0.14.2
Summary: AnyWikiDraw 0.14 (XStatic packaging standard)
Home-page: http://sourceforge.net/projects/anywikidraw
Maintainer: Reimar Bauer
Maintainer-email: rb.proj@googlemail.com
License: (same as AnyWikiDraw)
Keywords: anywikidraw xstatic
Platform: any
Dynamic: description
Dynamic: home-page
Dynamic: keywords
Dynamic: license
Dynamic: maintainer
Dynamic: maintainer-email
Dynamic: platform
Dynamic: summary
